{
  "agreements": [
    {
      "cop": null,
      "level": 350,
      "adep": null,
      "ades": [
        "LOWW"
      ],
      "transferType": null,
      "qnh": null,
      "vertical": false,
      "fromSector": "ed/ALP1",
      "toSector": "lo/W3",
      "remarks": "",
      "rfl": null,
      "runways": null,
      "routeBefore": null,
      "routeAfter": null,
      "releases": null
    },
    {
      "cop": null,
      "level": 350,
      "adep": null,
      "ades": [
        "LDZA",
        "LDRI",
        "LJMB",
        "LIP*"
      ],
      "transferType": null,
      "qnh": null,
      "vertical": false,
      "fromSector": "ed/ALP1",
      "toSector": "lo/W3",
      "remarks": "except LIPQ",
      "rfl": null,
      "runways": null,
      "routeBefore": null,
      "routeAfter": null,
      "releases": null
    },
    {
      "cop": null,
      "level": 330,
      "adep": [
        "LSZH",
        "LSZS",
        "LSMD"
      ],
      "ades": null,
      "transferType": "C",
      "qnh": null,
      "vertical": false,
      "fromSector": "ed/ALP1",
      "toSector": "lo/W2",
      "remarks": "FL310A",
      "rfl": null,
      "runways": null,
      "routeBefore": null,
      "routeAfter": null,
      "releases": null
    },
    {
      "cop": null,
      "level": 330,
      "adep": null,
      "ades": [
        "LOWG",
        "LOWK",
        "LOXZ",
        "LJLJ",
        "LIPQ"
      ],
      "transferType": null,
      "qnh": null,
      "vertical": false,
      "fromSector": "ed/ALP1",
      "toSector": "lo/W2",
      "remarks": "",
      "rfl": null,
      "runways": null,
      "routeBefore": null,
      "routeAfter": null,
      "releases": null
    },
    {
      "cop": null,
      "level": 330,
      "adep": null,
      "ades": [
        "LOWG",
        "LOWK",
        "LOXZ",
        "LJLJ",
        "LIPQ"
      ],
      "transferType": null,
      "qnh": null,
      "vertical": false,
      "fromSector": "ed/CHI1",
      "toSector": "lo/W2",
      "remarks": "",
      "rfl": null,
      "runways": null,
      "routeBefore": null,
      "routeAfter": null,
      "releases": null
    },
    {
      "cop": null,
      "level": 350,
      "adep": null,
      "ades": [
        "LDZA. LDRI",
        "LJMB",
        "LIP*"
      ],
      "transferType": null,
      "qnh": null,
      "vertical": false,
      "fromSector": "ed/CHI1",
      "toSector": "lo/W3",
      "remarks": "except LIPQ",
      "rfl": null,
      "runways": null,
      "routeBefore": null,
      "routeAfter": null,
      "releases": null
    },
    {
      "cop": null,
      "level": 330,
      "adep": null,
      "ades": [
        "LOWG",
        "LOWK",
        "LOXZ"
      ],
      "transferType": null,
      "qnh": null,
      "vertical": false,
      "fromSector": "ed/CHI1",
      "toSector": "lo/B2",
      "remarks": "",
      "rfl": null,
      "runways": null,
      "routeBefore": null,
      "routeAfter": null,
      "releases": null
    },
    {
      "cop": null,
      "level": 350,
      "adep": null,
      "ades": [
        "LDZA",
        "LJMB"
      ],
      "transferType": null,
      "qnh": null,
      "vertical": false,
      "fromSector": "ed/CHI1",
      "toSector": "lo/B3",
      "remarks": "",
      "rfl": null,
      "runways": null,
      "routeBefore": null,
      "routeAfter": null,
      "releases": null
    },
    {
      "cop": null,
      "level": 330,
      "adep": null,
      "ades": [
        "LOWW"
      ],
      "transferType": null,
      "qnh": null,
      "vertical": false,
      "fromSector": "ed/CHI1",
      "toSector": "lo/B2",
      "remarks": "",
      "rfl": null,
      "runways": null,
      "routeBefore": null,
      "routeAfter": null,
      "releases": null
    },
    {
      "cop": null,
      "level": 350,
      "adep": null,
      "ades": [
        "LOWW"
      ],
      "transferType": null,
      "qnh": null,
      "vertical": false,
      "fromSector": "ed/CHI1",
      "toSector": "lo/W3",
      "remarks": "",
      "rfl": null,
      "runways": null,
      "routeBefore": null,
      "routeAfter": null,
      "releases": null
    },
    {
      "cop": null,
      "level": 330,
      "adep": null,
      "ades": [
        "LOWG",
        "LOWK",
        "LOXZ"
      ],
      "transferType": null,
      "qnh": null,
      "vertical": false,
      "fromSector": "ed/DON1",
      "toSector": "lo/N2",
      "remarks": "",
      "rfl": null,
      "runways": null,
      "routeBefore": null,
      "routeAfter": null,
      "releases": null
    },
    {
      "cop": null,
      "level": 330,
      "adep": null,
      "ades": [
        "LOWW"
      ],
      "transferType": null,
      "qnh": null,
      "vertical": false,
      "fromSector": "ed/DON1",
      "toSector": "lo/N2",
      "remarks": "",
      "rfl": null,
      "runways": null,
      "routeBefore": null,
      "routeAfter": null,
      "releases": null
    },
    {
      "cop": null,
      "level": 350,
      "adep": null,
      "ades": [
        "LOWW"
      ],
      "transferType": null,
      "qnh": null,
      "vertical": false,
      "fromSector": "ed/ALP1",
      "toSector": "lo/W3",
      "remarks": "",
      "rfl": null,
      "runways": null,
      "routeBefore": null,
      "routeAfter": null,
      "releases": null
    }
  ]
}
