{
  "agreements": [
    {
      "cop": "DKB",
      "level": 250,
      "adep": null,
      "ades": [
        "EDDM"
      ],
      "transferType": null,
      "qnh": null,
      "vertical": false,
      "fromSector": "ed/WUR1",
      "toSector": "ed/WLD",
      "remarks": "",
      "rfl": null,
      "runways": null,
      "routeBefore": null,
      "routeAfter": null,
      "releases": null
    },
    {
      "cop": "ELMOX",
      "level": 250,
      "adep": null,
      "ades": [
        "EDDM"
      ],
      "transferType": null,
      "qnh": null,
      "vertical": false,
      "fromSector": "ed/WUR1",
      "toSector": "ed/WLD",
      "remarks": "Clearance to descend via ELMOX STAR by Langen, if traffic permits",
      "rfl": null,
      "runways": null,
      "routeBefore": null,
      "routeAfter": null,
      "releases": null
    },
    {
      "cop": "GESLU",
      "level": 250,
      "adep": null,
      "ades": [
        "EDDM"
      ],
      "transferType": null,
      "qnh": null,
      "vertical": false,
      "fromSector": "ed/TGO1",
      "toSector": "ed/NDG",
      "remarks": "",
      "rfl": null,
      "runways": null,
      "routeBefore": null,
      "routeAfter": null,
      "releases": null
    },
    {
      "cop": "TAMEB",
      "level": 250,
      "adep": null,
      "ades": [
        "EDAC",
        "EDDP"
      ],
      "transferType": null,
      "qnh": null,
      "vertical": false,
      "fromSector": "ed/FUL1",
      "toSector": "ed/GER",
      "remarks": "5NM before TAMEB at FL250",
      "rfl": null,
      "runways": null,
      "routeBefore": null,
      "routeAfter": null,
      "releases": null
    },
    {
      "cop": "ERSIL",
      "level": 260,
      "adep": null,
      "ades": [
        "EDDP"
      ],
      "transferType": null,
      "qnh": null,
      "vertical": false,
      "fromSector": "ed/FUL1",
      "toSector": "ed/HAL",
      "remarks": "via ERSIL - ESEGU",
      "rfl": null,
      "runways": null,
      "routeBefore": null,
      "routeAfter": null,
      "releases": null
    },
    {
      "cop": "IBAGA",
      "level": 310,
      "adep": null,
      "ades": [
        "EDDP"
      ],
      "transferType": null,
      "qnh": null,
      "vertical": false,
      "fromSector": "ed/WUR1",
      "toSector": "ed/BBG",
      "remarks": "",
      "rfl": null,
      "runways": null,
      "routeBefore": null,
      "routeAfter": null,
      "releases": null
    },
    {
      "cop": "DKB",
      "level": 310,
      "adep": null,
      "ades": [
        "LOWI",
        "LOWS"
      ],
      "transferType": null,
      "qnh": null,
      "vertical": false,
      "fromSector": "ed/WUR1",
      "toSector": "ed/WLD",
      "remarks": "",
      "rfl": null,
      "runways": null,
      "routeBefore": null,
      "routeAfter": null,
      "releases": null
    },
    {
      "cop": "BATUB",
      "level": 310,
      "adep": null,
      "ades": [
        "LOWI",
        "LSZS",
        "LSZA",
        "LSZL",
        "LIPB"
      ],
      "transferType": null,
      "qnh": null,
      "vertical": false,
      "fromSector": "ed/TGO1",
      "toSector": "ed/FUE",
      "remarks": "",
      "rfl": null,
      "runways": null,
      "routeBefore": null,
      "routeAfter": null,
      "releases": null
    },
    {
      "cop": "UTABA",
      "level": 310,
      "adep": null,
      "ades": [
        "LOWI",
        "LSZS",
        "LSZA",
        "LSZL",
        "LIPB"
      ],
      "transferType": null,
      "qnh": null,
      "vertical": false,
      "fromSector": "ed/TGO1",
      "toSector": "ed/FUE",
      "remarks": "",
      "rfl": null,
      "runways": null,
      "routeBefore": null,
      "routeAfter": null,
      "releases": null
    },
    {
      "cop": "ERSIL",
      "level": 290,
      "adep": [
        "EDDF",
        "EDFE",
        "EDFZ",
        "ETOU"
      ],
      "ades": null,
      "transferType": null,
      "qnh": null,
      "vertical": false,
      "fromSector": "ed/FUL1",
      "toSector": "ed/HAL",
      "remarks": "released for climb FL310 inside FUL",
      "rfl": null,
      "runways": null,
      "routeBefore": null,
      "routeAfter": null,
      "releases": null
    },
    {
      "cop": "TAMEB",
      "level": 290,
      "adep": [
        "EDDF",
        "EDFE",
        "EDFZ",
        "ETOU"
      ],
      "ades": null,
      "transferType": null,
      "qnh": null,
      "vertical": false,
      "fromSector": "ed/FUL1",
      "toSector": "ed/GER",
      "remarks": "released for climb FL310 inside FUL",
      "rfl": null,
      "runways": null,
      "routeBefore": null,
      "routeAfter": null,
      "releases": null
    },
    {
      "cop": "KULOK",
      "level": 320,
      "adep": null,
      "ades": [
        "EDDC",
        "EDAB"
      ],
      "transferType": null,
      "qnh": null,
      "vertical": false,
      "fromSector": "ed/ERL1",
      "toSector": "ed/HOF",
      "remarks": "10 NM prior KULOK at level",
      "rfl": null,
      "runways": null,
      "routeBefore": null,
      "routeAfter": null,
      "releases": null
    },
    {
      "cop": "BAROB",
      "level": 320,
      "adep": null,
      "ades": [
        "LKPR",
        "LKKB",
        "LKVO",
        "LKPD",
        "LKCV",
        "LKHK",
        "LKMH"
      ],
      "transferType": null,
      "qnh": null,
      "vertical": false,
      "fromSector": "ed/ERL1",
      "toSector": "ed/HOF",
      "remarks": "TONSU at level. Arrivals LKPR group may be cleared direct ODOMO.",
      "rfl": null,
      "runways": null,
      "routeBefore": null,
      "routeAfter": null,
      "releases": null
    },
    {
      "cop": "ABERU",
      "level": 320,
      "adep": null,
      "ades": [
        "EDDM",
        "EDMA",
        "EDMO"
      ],
      "transferType": null,
      "qnh": null,
      "vertical": false,
      "fromSector": "ed/ERL1",
      "toSector": "ed/HOF",
      "remarks": "",
      "rfl": null,
      "runways": null,
      "routeBefore": null,
      "routeAfter": null,
      "releases": null
    },
    {
      "cop": "NURGO",
      "level": 320,
      "adep": null,
      "ades": [
        "EDDF"
      ],
      "transferType": null,
      "qnh": null,
      "vertical": false,
      "fromSector": "ed/ERL1",
      "toSector": "ed/HOF",
      "remarks": "",
      "rfl": null,
      "runways": null,
      "routeBefore": null,
      "routeAfter": null,
      "releases": null
    },
    {
      "cop": "SODRO",
      "level": 320,
      "adep": null,
      "ades": [
        "EDDF"
      ],
      "transferType": null,
      "qnh": null,
      "vertical": false,
      "fromSector": "ed/ERL1",
      "toSector": "ed/BBG",
      "remarks": "",
      "rfl": null,
      "runways": null,
      "routeBefore": null,
      "routeAfter": null,
      "releases": null
    },
    {
      "cop": "UNAVI",
      "level": 320,
      "adep": null,
      "ades": [
        "EDDF",
        "ETAR"
      ],
      "transferType": null,
      "qnh": null,
      "vertical": false,
      "fromSector": "ed/ERL1",
      "toSector": "ed/HOF",
      "remarks": "",
      "rfl": null,
      "runways": null,
      "routeBefore": null,
      "routeAfter": null,
      "releases": null
    },
    {
      "cop": "MADEB",
      "level": 320,
      "adep": null,
      "ades": [
        "LIMC",
        "LIML",
        "LIME"
      ],
      "transferType": null,
      "qnh": null,
      "vertical": false,
      "fromSector": "ed/ALP1",
      "toSector": "ed/ZUG",
      "remarks": "",
      "rfl": null,
      "runways": null,
      "routeBefore": null,
      "routeAfter": null,
      "releases": null
    },
    {
      "cop": "BERAS",
      "level": 320,
      "adep": null,
      "ades": [
        "LIPZ",
        "LIPH",
        "LIPX",
        "LIPO",
        "LIPA"
      ],
      "transferType": null,
      "qnh": null,
      "vertical": false,
      "fromSector": "ed/ALP1",
      "toSector": "ed/TEG",
      "remarks": "",
      "rfl": null,
      "runways": null,
      "routeBefore": null,
      "routeAfter": null,
      "releases": null
    },
    {
      "cop": "TULSI",
      "level": 320,
      "adep": null,
      "ades": [
        "LSZS",
        "LSZA",
        "LIPB"
      ],
      "transferType": null,
      "qnh": null,
      "vertical": false,
      "fromSector": "ed/CHI1",
      "toSector": "ed/TEG",
      "remarks": "abeam MANAL at FL320",
      "rfl": null,
      "runways": null,
      "routeBefore": null,
      "routeAfter": null,
      "releases": null
    },
    {
      "cop": "MADEB",
      "level": 320,
      "adep": null,
      "ades": [
        "LIPZ",
        "LIPH",
        "LIPX",
        "LIPO",
        "LIPA"
      ],
      "transferType": null,
      "qnh": null,
      "vertical": false,
      "fromSector": "ed/ALP1",
      "toSector": "ed/ZUG",
      "remarks": "",
      "rfl": null,
      "runways": null,
      "routeBefore": null,
      "routeAfter": null,
      "releases": null
    },
    {
      "cop": "KPT",
      "level": 320,
      "adep": null,
      "ades": [
        "LFST",
        "LSZB"
      ],
      "transferType": null,
      "qnh": null,
      "vertical": false,
      "fromSector": "ed/ALP1",
      "toSector": "ed/FUE",
      "remarks": "L856",
      "rfl": null,
      "runways": null,
      "routeBefore": null,
      "routeAfter": null,
      "releases": null
    },
    {
      "cop": "KPT",
      "level": 320,
      "adep": null,
      "ades": [
        "LSZH"
      ],
      "transferType": null,
      "qnh": null,
      "vertical": false,
      "fromSector": "ed/ALP1",
      "toSector": "ed/FUE",
      "remarks": "P66, 20 NM prior KPT at level.",
      "rfl": null,
      "runways": null,
      "routeBefore": null,
      "routeAfter": null,
      "releases": null
    },
    {
      "cop": "MOGTI",
      "level": 320,
      "adep": null,
      "ades": [
        "EDDS"
      ],
      "transferType": null,
      "qnh": null,
      "vertical": false,
      "fromSector": "ed/ALP1",
      "toSector": "ed/ZUG",
      "remarks": "10 NM prior MOGTI at level.",
      "rfl": null,
      "runways": null,
      "routeBefore": null,
      "routeAfter": null,
      "releases": null
    },
    {
      "cop": "KPT",
      "level": 320,
      "adep": null,
      "ades": [
        "EDSB",
        "LSZS",
        "EDFM",
        "ETAR",
        "EDTD",
        "EDTL",
        "EDRY"
      ],
      "transferType": null,
      "qnh": null,
      "vertical": false,
      "fromSector": "ed/ALP1",
      "toSector": "ed/FUE",
      "remarks": "P66/L856, 15 NM prior KPT at level.",
      "rfl": null,
      "runways": null,
      "routeBefore": null,
      "routeAfter": null,
      "releases": null
    },
    {
      "cop": "MAH",
      "level": 320,
      "adep": null,
      "ades": [
        "EDDS",
        "EDSB",
        "EDDR",
        "EDRY",
        "EDRZ",
        "EDFM",
        "EDTY",
        "ETAD",
        "ETAR"
      ],
      "transferType": null,
      "qnh": null,
      "vertical": false,
      "fromSector": "ed/ISA1",
      "toSector": "ed/NDG",
      "remarks": "OTT at FL320",
      "rfl": null,
      "runways": null,
      "routeBefore": null,
      "routeAfter": null,
      "releases": null
    },
    {
      "cop": "OLASO",
      "level": 320,
      "adep": null,
      "ades": [
        "EDDF"
      ],
      "transferType": null,
      "qnh": null,
      "vertical": false,
      "fromSector": "ed/ALP1",
      "toSector": "ed/ZUG",
      "remarks": "20 NM prior OLASO at level.",
      "rfl": null,
      "runways": null,
      "routeBefore": null,
      "routeAfter": null,
      "releases": null
    },
    {
      "cop": "TEKSI",
      "level": 320,
      "adep": null,
      "ades": [
        "EDDF"
      ],
      "transferType": null,
      "qnh": null,
      "vertical": false,
      "fromSector": "ed/ISA1",
      "toSector": "ed/NDG",
      "remarks": "25 NM prior TEKSI at level.",
      "rfl": null,
      "runways": null,
      "routeBefore": null,
      "routeAfter": null,
      "releases": null
    },
    {
      "cop": "KOGOL",
      "level": 320,
      "adep": null,
      "ades": [
        "EDDS",
        "EDSB",
        "EDRY",
        "EDTY",
        "EDFM"
      ],
      "transferType": null,
      "qnh": null,
      "vertical": false,
      "fromSector": "ed/CHI1",
      "toSector": "ed/STA",
      "remarks": "",
      "rfl": null,
      "runways": null,
      "routeBefore": null,
      "routeAfter": null,
      "releases": null
    },
    {
      "cop": "KPT",
      "level": 320,
      "adep": null,
      "ades": [
        "EDDS",
        "EDSB",
        "EDRY",
        "EDTY",
        "EDFM"
      ],
      "transferType": null,
      "qnh": null,
      "vertical": false,
      "fromSector": "ed/ALP1",
      "toSector": "ed/FUE",
      "remarks": "L608, 30 NM prior KPT at level.",
      "rfl": null,
      "runways": null,
      "routeBefore": null,
      "routeAfter": null,
      "releases": null
    },
    {
      "cop": "MOMUK",
      "level": 320,
      "adep": null,
      "ades": [
        "LOWS"
      ],
      "transferType": null,
      "qnh": null,
      "vertical": false,
      "fromSector": "ed/ALP1",
      "toSector": "ed/ZUG",
      "remarks": "15 NM prior BEMKI at level.",
      "rfl": null,
      "runways": null,
      "routeBefore": null,
      "routeAfter": null,
      "releases": null
    },
    {
      "cop": "BESNI",
      "level": 320,
      "adep": null,
      "ades": [
        "LOWL"
      ],
      "transferType": null,
      "qnh": null,
      "vertical": false,
      "fromSector": "ed/ISA1",
      "toSector": "ed/NDG",
      "remarks": "",
      "rfl": null,
      "runways": null,
      "routeBefore": null,
      "routeAfter": null,
      "releases": null
    },
    {
      "cop": "TULSI",
      "level": 320,
      "adep": null,
      "ades": [
        "LOWL"
      ],
      "transferType": null,
      "qnh": null,
      "vertical": false,
      "fromSector": "ed/CHI1",
      "toSector": "ed/TEG",
      "remarks": "",
      "rfl": null,
      "runways": null,
      "routeBefore": null,
      "routeAfter": null,
      "releases": null
    },
    {
      "cop": "KOGOL",
      "level": 320,
      "adep": null,
      "ades": [
        "EDDN",
        "EDDS",
        "EDTY",
        "EDQD",
        "EDQM",
        "EDQC",
        "EDQK",
        "EDQT",
        "EDQG",
        "EDQA"
      ],
      "transferType": null,
      "qnh": null,
      "vertical": false,
      "fromSector": "ed/CHI1",
      "toSector": "ed/STA",
      "remarks": "NORIN at FL320",
      "rfl": null,
      "runways": null,
      "routeBefore": null,
      "routeAfter": null,
      "releases": null
    },
    {
      "cop": "RUDNO",
      "level": 320,
      "adep": null,
      "ades": [
        "LOWI"
      ],
      "transferType": null,
      "qnh": null,
      "vertical": false,
      "fromSector": "ed/DON1",
      "toSector": "ed/RDG",
      "remarks": "",
      "rfl": null,
      "runways": null,
      "routeBefore": null,
      "routeAfter": null,
      "releases": null
    },
    {
      "cop": "MAMOR",
      "level": 320,
      "adep": null,
      "ades": [
        "LKPR",
        "LKPD",
        "LKKB",
        "LKCV",
        "LKHK",
        "LKMH",
        "LKVO"
      ],
      "transferType": null,
      "qnh": null,
      "vertical": false,
      "fromSector": "ed/DON1",
      "toSector": "ed/RDG",
      "remarks": "",
      "rfl": null,
      "runways": null,
      "routeBefore": null,
      "routeAfter": null,
      "releases": null
    },
    {
      "cop": "NENUM",
      "level": 320,
      "adep": null,
      "ades": [
        "LKPR",
        "LKPD",
        "LKKB",
        "LKCV",
        "LKHK",
        "LKMH",
        "LKVO"
      ],
      "transferType": null,
      "qnh": null,
      "vertical": false,
      "fromSector": "ed/DON1",
      "toSector": "ed/EGG",
      "remarks": "",
      "rfl": null,
      "runways": null,
      "routeBefore": null,
      "routeAfter": null,
      "releases": null
    },
    {
      "cop": "STAUB",
      "level": 320,
      "adep": null,
      "ades": [
        "LKPR",
        "LKPD",
        "LKKB",
        "LKCV",
        "LKHK",
        "LKMH",
        "LKVO"
      ],
      "transferType": null,
      "qnh": null,
      "vertical": false,
      "fromSector": "ed/DON1",
      "toSector": "ed/RDG",
      "remarks": "",
      "rfl": null,
      "runways": null,
      "routeBefore": null,
      "routeAfter": null,
      "releases": null
    },
    {
      "cop": "MAH",
      "level": 320,
      "adep": null,
      "ades": [
        "LKKV"
      ],
      "transferType": null,
      "qnh": null,
      "vertical": false,
      "fromSector": "ed/ISA1",
      "toSector": "ed/NDG",
      "remarks": "",
      "rfl": null,
      "runways": null,
      "routeBefore": null,
      "routeAfter": null,
      "releases": null
    },
    {
      "cop": "MAH",
      "level": 320,
      "adep": null,
      "ades": [
        "ETAR",
        "EDGS",
        "EDRK"
      ],
      "transferType": null,
      "qnh": null,
      "vertical": false,
      "fromSector": "ed/ISA1",
      "toSector": "ed/NDG",
      "remarks": "",
      "rfl": null,
      "runways": null,
      "routeBefore": null,
      "routeAfter": null,
      "releases": null
    },
    {
      "cop": "TALAL",
      "level": 320,
      "adep": null,
      "ades": [
        "EDDF",
        "ETOU",
        "EDFE",
        "EDFZ"
      ],
      "transferType": null,
      "qnh": null,
      "vertical": false,
      "fromSector": "ed/DON1",
      "toSector": "ed/ALB",
      "remarks": "",
      "rfl": null,
      "runways": null,
      "routeBefore": null,
      "routeAfter": null,
      "releases": null
    },
    {
      "cop": "STAUB",
      "level": 320,
      "adep": null,
      "ades": [
        "EDQG"
      ],
      "transferType": null,
      "qnh": null,
      "vertical": false,
      "fromSector": "ed/DON1",
      "toSector": "ed/RDG",
      "remarks": "",
      "rfl": null,
      "runways": null,
      "routeBefore": null,
      "routeAfter": null,
      "releases": null
    },
    {
      "cop": "RUDNO",
      "level": 320,
      "adep": null,
      "ades": [
        "EDFQ",
        "EDGS",
        "EDDE",
        "EDDP",
        "EDVK"
      ],
      "transferType": null,
      "qnh": null,
      "vertical": false,
      "fromSector": "ed/DON1",
      "toSector": "ed/RDG",
      "remarks": "",
      "rfl": null,
      "runways": null,
      "routeBefore": null,
      "routeAfter": null,
      "releases": null
    },
    {
      "cop": "BESIP",
      "level": 320,
      "adep": null,
      "ades": [
        "EDDB",
        "EDAY"
      ],
      "transferType": null,
      "qnh": null,
      "vertical": false,
      "fromSector": "ed/SPE1",
      "toSector": "ed/MEI",
      "remarks": "Not later than 10 NM prior BESIP at FL320",
      "rfl": null,
      "runways": null,
      "routeBefore": null,
      "routeAfter": null,
      "releases": null
    },
    {
      "cop": "PIKIB",
      "level": 320,
      "adep": null,
      "ades": [
        "EDDN"
      ],
      "transferType": null,
      "qnh": null,
      "vertical": false,
      "fromSector": "ed/SPE1",
      "toSector": "ed/MEI",
      "remarks": "",
      "rfl": null,
      "runways": null,
      "routeBefore": null,
      "routeAfter": null,
      "releases": null
    },
    {
      "cop": "BEBKU",
      "level": 320,
      "adep": null,
      "ades": [
        "EDQD",
        "EDQM",
        "EDQC",
        "EDQK",
        "EDQT",
        "EDQG",
        "EDQA",
        "ETIC",
        "ETIN",
        "ETHN",
        "LKKV",
        "LKCS"
      ],
      "transferType": null,
      "qnh": null,
      "vertical": false,
      "fromSector": "ed/SPE1",
      "toSector": "ed/MEI",
      "remarks": "",
      "rfl": null,
      "runways": null,
      "routeBefore": null,
      "routeAfter": null,
      "releases": null
    },
    {
      "cop": "BEBKU",
      "level": 320,
      "adep": null,
      "ades": [
        "EPWR"
      ],
      "transferType": null,
      "qnh": null,
      "vertical": false,
      "fromSector": "ed/SPE1",
      "toSector": "ed/MEI",
      "remarks": "KOBUS at FL320",
      "rfl": null,
      "runways": null,
      "routeBefore": null,
      "routeAfter": null,
      "releases": null
    },
    {
      "cop": "EKPEK",
      "level": 320,
      "adep": null,
      "ades": [
        "EPWR",
        "LKCS"
      ],
      "transferType": null,
      "qnh": null,
      "vertical": false,
      "fromSector": "ed/SPE1",
      "toSector": "ed/MEI",
      "remarks": "",
      "rfl": null,
      "runways": null,
      "routeBefore": null,
      "routeAfter": null,
      "releases": null
    },
    {
      "cop": "KOBUS",
      "level": 320,
      "adep": null,
      "ades": [
        "EPWR",
        "EPPO"
      ],
      "transferType": null,
      "qnh": null,
      "vertical": false,
      "fromSector": "ed/SPE1",
      "toSector": "ed/MEI",
      "remarks": "",
      "rfl": null,
      "runways": null,
      "routeBefore": null,
      "routeAfter": null,
      "releases": null
    },
    {
      "cop": "RENDO",
      "level": 320,
      "adep": null,
      "ades": [
        "LKCS"
      ],
      "transferType": null,
      "qnh": null,
      "vertical": false,
      "fromSector": "ed/SPE1",
      "toSector": "ed/MEI",
      "remarks": "",
      "rfl": null,
      "runways": null,
      "routeBefore": null,
      "routeAfter": null,
      "releases": null
    },
    {
      "cop": "RIVSA",
      "level": 320,
      "adep": null,
      "ades": [
        "LKCS"
      ],
      "transferType": null,
      "qnh": null,
      "vertical": false,
      "fromSector": "ed/SPE1",
      "toSector": "ed/MEI",
      "remarks": "",
      "rfl": null,
      "runways": null,
      "routeBefore": null,
      "routeAfter": null,
      "releases": null
    },
    {
      "cop": "EBASA",
      "level": 320,
      "adep": null,
      "ades": [
        "LKPR",
        "LKKB",
        "LKCS",
        "LKVO",
        "LKPD",
        "LKCV",
        "LKHK",
        "LKMH"
      ],
      "transferType": null,
      "qnh": null,
      "vertical": false,
      "fromSector": "ed/SPE1",
      "toSector": "ed/MEI",
      "remarks": "",
      "rfl": null,
      "runways": null,
      "routeBefore": null,
      "routeAfter": null,
      "releases": null
    },
    {
      "cop": "OSKAN",
      "level": 320,
      "adep": null,
      "ades": [
        "LKPR",
        "LKKB",
        "LKCS",
        "LKVO",
        "LKPD",
        "LKCV",
        "LKHK",
        "LKMH"
      ],
      "transferType": null,
      "qnh": null,
      "vertical": false,
      "fromSector": "ed/SPE1",
      "toSector": "ed/MEI",
      "remarks": "",
      "rfl": null,
      "runways": null,
      "routeBefore": null,
      "routeAfter": null,
      "releases": null
    },
    {
      "cop": "GOLAT",
      "level": 320,
      "adep": null,
      "ades": [
        "EDDB"
      ],
      "transferType": null,
      "qnh": null,
      "vertical": false,
      "fromSector": "ed/SAL1",
      "toSector": "ed/GER",
      "remarks": "",
      "rfl": null,
      "runways": null,
      "routeBefore": null,
      "routeAfter": null,
      "releases": null
    },
    {
      "cop": "RELKO",
      "level": 320,
      "adep": null,
      "ades": [
        "EDDB",
        "EDAY",
        "EDAZ"
      ],
      "transferType": null,
      "qnh": null,
      "vertical": false,
      "fromSector": "ed/SAL1",
      "toSector": "ed/GER",
      "remarks": "",
      "rfl": null,
      "runways": null,
      "routeBefore": null,
      "routeAfter": null,
      "releases": null
    },
    {
      "cop": "NIMAB",
      "level": 320,
      "adep": null,
      "ades": [
        "EDDF",
        "ETOU",
        "EDFE",
        "EDFZ",
        "EDFQ"
      ],
      "transferType": null,
      "qnh": null,
      "vertical": false,
      "fromSector": "ed/SAL1",
      "toSector": "ed/HAL",
      "remarks": "",
      "rfl": null,
      "runways": null,
      "routeBefore": null,
      "routeAfter": null,
      "releases": null
    },
    {
      "cop": "OSKAT",
      "level": 320,
      "adep": null,
      "ades": [
        "EDDF",
        "ETOU",
        "EDFE",
        "EDFZ",
        "EDFQ"
      ],
      "transferType": null,
      "qnh": null,
      "vertical": false,
      "fromSector": "ed/SAL1",
      "toSector": "ed/HAL",
      "remarks": "",
      "rfl": null,
      "runways": null,
      "routeBefore": null,
      "routeAfter": null,
      "releases": null
    },
    {
      "cop": "SULED",
      "level": 320,
      "adep": null,
      "ades": [
        "EDDF",
        "ETOU",
        "EDFE",
        "EDFZ",
        "EDFQ"
      ],
      "transferType": null,
      "qnh": null,
      "vertical": false,
      "fromSector": "ed/SAL1",
      "toSector": "ed/GER",
      "remarks": "abeam NAMUB at FL320",
      "rfl": null,
      "runways": null,
      "routeBefore": null,
      "routeAfter": null,
      "releases": null
    },
    {
      "cop": "TOGRO",
      "level": 320,
      "adep": null,
      "ades": [
        "EDDN",
        "EDQ*",
        "ETIC"
      ],
      "transferType": null,
      "qnh": null,
      "vertical": false,
      "fromSector": "ed/SAL1",
      "toSector": "ed/GER",
      "remarks": "",
      "rfl": null,
      "runways": null,
      "routeBefore": null,
      "routeAfter": null,
      "releases": null
    },
    {
      "cop": "NARUS",
      "level": 320,
      "adep": null,
      "ades": [
        "EDDV",
        "EDVE",
        "EDBM",
        "ETNW"
      ],
      "transferType": null,
      "qnh": null,
      "vertical": false,
      "fromSector": "ed/SAL1",
      "toSector": "ed/GER",
      "remarks": "",
      "rfl": null,
      "runways": null,
      "routeBefore": null,
      "routeAfter": null,
      "releases": null
    },
    {
      "cop": "GALMA",
      "level": 320,
      "adep": null,
      "ades": [
        "EDMS",
        "ETHN",
        "ETIN",
        "LKKV"
      ],
      "transferType": null,
      "qnh": null,
      "vertical": false,
      "fromSector": "ed/SAL1",
      "toSector": "ed/HAL",
      "remarks": "",
      "rfl": null,
      "runways": null,
      "routeBefore": null,
      "routeAfter": null,
      "releases": null
    },
    {
      "cop": "RELKO",
      "level": 320,
      "adep": null,
      "ades": [
        "ETSI",
        "ETSN"
      ],
      "transferType": null,
      "qnh": null,
      "vertical": false,
      "fromSector": "ed/SAL1",
      "toSector": "ed/GER",
      "remarks": "",
      "rfl": null,
      "runways": null,
      "routeBefore": null,
      "routeAfter": null,
      "releases": null
    },
    {
      "cop": "SULED",
      "level": 320,
      "adep": null,
      "ades": [
        "ETSI",
        "ETSN"
      ],
      "transferType": null,
      "qnh": null,
      "vertical": false,
      "fromSector": "ed/SAL1",
      "toSector": "ed/GER",
      "remarks": "",
      "rfl": null,
      "runways": null,
      "routeBefore": null,
      "routeAfter": null,
      "releases": null
    },
    {
      "cop": "OSTRA",
      "level": 320,
      "adep": null,
      "ades": [
        "LKPR",
        "LKKB",
        "LKCS",
        "LKVO",
        "LKPD",
        "LKCV",
        "LKHK",
        "LKMH"
      ],
      "transferType": null,
      "qnh": null,
      "vertical": false,
      "fromSector": "ed/SPE1",
      "toSector": "ed/GER",
      "remarks": "Latest at boundary SAL/SPE",
      "rfl": null,
      "runways": null,
      "routeBefore": null,
      "routeAfter": null,
      "releases": null
    },
    {
      "cop": "TALEG",
      "level": 320,
      "adep": null,
      "ades": [
        "LKPR",
        "LKKB",
        "LKCS",
        "LKVO",
        "LKPD",
        "LKCV",
        "LKHK",
        "LKMH"
      ],
      "transferType": null,
      "qnh": null,
      "vertical": false,
      "fromSector": "ed/SPE1",
      "toSector": "ed/GER",
      "remarks": "Latest at boundary SAL/SPE",
      "rfl": null,
      "runways": null,
      "routeBefore": null,
      "routeAfter": null,
      "releases": null
    },
    {
      "cop": "KPT",
      "level": 320,
      "adep": null,
      "ades": [
        "LFSB",
        "LFGA",
        "LFGB",
        "LFSM",
        "EDTG",
        "LSGC",
        "LSZ* (EXCL. LSZH)",
        "LSM* (EXCL. LSMD)"
      ],
      "transferType": null,
      "qnh": null,
      "vertical": false,
      "fromSector": "ed/ALP1",
      "toSector": "ed/FUE",
      "remarks": "",
      "rfl": null,
      "runways": null,
      "routeBefore": null,
      "routeAfter": null,
      "releases": null
    },
    {
      "cop": "KPT",
      "level": 320,
      "adep": null,
      "ades": [
        "LSZH",
        "LSMD"
      ],
      "transferType": null,
      "qnh": null,
      "vertical": false,
      "fromSector": "ed/ALP1",
      "toSector": "ed/FUE",
      "remarks": "L856/L608, 30NM prior KPT at FL320",
      "rfl": null,
      "runways": null,
      "routeBefore": null,
      "routeAfter": null,
      "releases": null
    },
    {
      "cop": "TIVDA",
      "level": 320,
      "adep": null,
      "ades": [
        "LOWS"
      ],
      "transferType": null,
      "qnh": null,
      "vertical": false,
      "fromSector": "ed/DON1",
      "toSector": "ed/RDG",
      "remarks": "ARMUT at FL320",
      "rfl": null,
      "runways": null,
      "routeBefore": null,
      "routeAfter": null,
      "releases": null
    },
    {
      "cop": "TIVDA",
      "level": 320,
      "adep": null,
      "ades": [
        "LOWL"
      ],
      "transferType": null,
      "qnh": null,
      "vertical": false,
      "fromSector": "ed/DON1",
      "toSector": "ed/RDG",
      "remarks": "ARMUT at FL320",
      "rfl": null,
      "runways": null,
      "routeBefore": null,
      "routeAfter": null,
      "releases": null
    },
    {
      "cop": "RUDNO",
      "level": 320,
      "adep": null,
      "ades": [
        "EDDC",
        "EDAB"
      ],
      "transferType": null,
      "qnh": null,
      "vertical": false,
      "fromSector": "ed/DON1",
      "toSector": "ed/RDG",
      "remarks": "10NM prior RUDNO at FL320",
      "rfl": null,
      "runways": null,
      "routeBefore": null,
      "routeAfter": null,
      "releases": null
    },
    {
      "cop": "ERNAS",
      "level": 320,
      "adep": null,
      "ades": [
        "EDDF"
      ],
      "transferType": null,
      "qnh": null,
      "vertical": false,
      "fromSector": "ed/DON1",
      "toSector": "ed/ALB",
      "remarks": "abeam GOLMO at FL320",
      "rfl": null,
      "runways": null,
      "routeBefore": null,
      "routeAfter": null,
      "releases": null
    },
    {
      "cop": "ERNAS",
      "level": 320,
      "adep": null,
      "ades": [
        "EDDF",
        "ETOU",
        "EDFE",
        "EDFZ"
      ],
      "transferType": null,
      "qnh": null,
      "vertical": false,
      "fromSector": "ed/DON1",
      "toSector": "ed/ALB",
      "remarks": "TALAL at FL320",
      "rfl": null,
      "runways": null,
      "routeBefore": null,
      "routeAfter": null,
      "releases": null
    },
    {
      "cop": "ERMEL",
      "level": 320,
      "adep": null,
      "ades": [
        "EDDF"
      ],
      "transferType": null,
      "qnh": null,
      "vertical": false,
      "fromSector": "ed/DON1",
      "toSector": "ed/ALB",
      "remarks": "10NM prior ERMEL at FL320",
      "rfl": null,
      "runways": null,
      "routeBefore": null,
      "routeAfter": null,
      "releases": null
    },
    {
      "cop": "UNKUL",
      "level": 320,
      "adep": null,
      "ades": [
        "EDSB",
        "EDDR",
        "EDRZ"
      ],
      "transferType": null,
      "qnh": null,
      "vertical": false,
      "fromSector": "ed/DON1",
      "toSector": "ed/ALB",
      "remarks": "UPALA at FL320",
      "rfl": null,
      "runways": null,
      "routeBefore": null,
      "routeAfter": null,
      "releases": null
    },
    {
      "cop": "UPALA",
      "level": 320,
      "adep": null,
      "ades": [
        "EDDP",
        "EDAC",
        "EDDE",
        "EDDK",
        "EDFQ",
        "EDLW",
        "EDLA",
        "EDKZ",
        "EDLP",
        "EDLI",
        "EDVK"
      ],
      "transferType": null,
      "qnh": null,
      "vertical": false,
      "fromSector": "ed/DON1",
      "toSector": "ed/ALB",
      "remarks": "10 NM prior UPALA at FL320",
      "rfl": null,
      "runways": null,
      "routeBefore": null,
      "routeAfter": null,
      "releases": null
    },
    {
      "cop": "VEVAS",
      "level": 300,
      "adep": null,
      "ades": [
        "EDDN",
        "EDQD",
        "EDQM",
        "EDQC",
        "EDQK",
        "EDQT",
        "EDQG",
        "EDQA",
        "ETIC"
      ],
      "transferType": null,
      "qnh": null,
      "vertical": false,
      "fromSector": "ed/HVL1",
      "toSector": "ed/GER",
      "remarks": "",
      "rfl": null,
      "runways": null,
      "routeBefore": null,
      "routeAfter": null,
      "releases": null
    },
    {
      "cop": "MAG",
      "level": 300,
      "adep": null,
      "ades": [
        "EDDN",
        "EDQD",
        "EDQM",
        "EDQC",
        "EDQK",
        "EDQT",
        "EDQG",
        "EDQA",
        "ETIC",
        "EDDE"
      ],
      "transferType": null,
      "qnh": null,
      "vertical": false,
      "fromSector": "ed/HVL1",
      "toSector": "ed/HAL",
      "remarks": "",
      "rfl": null,
      "runways": null,
      "routeBefore": null,
      "routeAfter": null,
      "releases": null
    },
    {
      "cop": "MAG",
      "level": 300,
      "adep": null,
      "ades": [
        "ELLX"
      ],
      "transferType": null,
      "qnh": null,
      "vertical": false,
      "fromSector": "ed/HVL1",
      "toSector": "ed/HAL",
      "remarks": "",
      "rfl": null,
      "runways": null,
      "routeBefore": null,
      "routeAfter": null,
      "releases": null
    },
    {
      "cop": "TOPDI",
      "level": 300,
      "adep": null,
      "ades": [
        "EDDF",
        "ETOU",
        "EDFE",
        "EDFZ",
        "EDFQ"
      ],
      "transferType": null,
      "qnh": null,
      "vertical": false,
      "fromSector": "ed/HVL1",
      "toSector": "ed/HAL",
      "remarks": "",
      "rfl": null,
      "runways": null,
      "routeBefore": null,
      "routeAfter": null,
      "releases": null
    },
    {
      "cop": "DIDGI",
      "level": 300,
      "adep": null,
      "ades": [
        "EDDF",
        "ETOU",
        "EDFE",
        "EDFZ",
        "EDFQ"
      ],
      "transferType": null,
      "qnh": null,
      "vertical": false,
      "fromSector": "ed/HVL1",
      "toSector": "ed/HAL",
      "remarks": "",
      "rfl": null,
      "runways": null,
      "routeBefore": null,
      "routeAfter": null,
      "releases": null
    },
    {
      "cop": "KOMIB",
      "level": 250,
      "adep": null,
      "ades": [
        "LKKV",
        "EDMS"
      ],
      "transferType": null,
      "qnh": null,
      "vertical": false,
      "fromSector": "ed/WUR1",
      "toSector": "ed/BBG",
      "remarks": "",
      "rfl": null,
      "runways": null,
      "routeBefore": null,
      "routeAfter": null,
      "releases": null
    },
    {
      "cop": "ELVAG",
      "level": 310,
      "adep": [
        "EDDF",
        "EDFE",
        "EDFZ",
        "ETOU"
      ],
      "ades": null,
      "transferType": "C",
      "qnh": null,
      "vertical": false,
      "fromSector": "ed/WUR1",
      "toSector": "ed/NDG",
      "remarks": "Out of FL240",
      "rfl": null,
      "runways": null,
      "routeBefore": null,
      "routeAfter": null,
      "releases": null
    },
    {
      "cop": "BARSU",
      "level": 270,
      "adep": [
        "ETAR",
        "ETOU"
      ],
      "ades": null,
      "transferType": null,
      "qnh": null,
      "vertical": false,
      "fromSector": "ed/WUR1",
      "toSector": "ed/BBG",
      "remarks": "",
      "rfl": null,
      "runways": null,
      "routeBefore": null,
      "routeAfter": null,
      "releases": null
    },
    {
      "cop": "FEDZA",
      "level": 260,
      "adep": null,
      "ades": [
        "EDDP"
      ],
      "transferType": null,
      "qnh": null,
      "vertical": false,
      "fromSector": "ed/FUL1",
      "toSector": "ed/HAL",
      "remarks": "",
      "rfl": null,
      "runways": null,
      "routeBefore": null,
      "routeAfter": null,
      "releases": null
    },
    {
      "cop": "FEDZA",
      "level": 250,
      "adep": null,
      "ades": [
        "EDBM"
      ],
      "transferType": null,
      "qnh": null,
      "vertical": false,
      "fromSector": "ed/FUL1",
      "toSector": "ed/HAL",
      "remarks": "",
      "rfl": null,
      "runways": null,
      "routeBefore": null,
      "routeAfter": null,
      "releases": null
    },
    {
      "cop": "GASKA",
      "level": 250,
      "adep": null,
      "ades": [
        "LKKV",
        "EDMS"
      ],
      "transferType": null,
      "qnh": null,
      "vertical": false,
      "fromSector": "ed/FUL1",
      "toSector": "ed/BBG",
      "remarks": "",
      "rfl": null,
      "runways": null,
      "routeBefore": null,
      "routeAfter": null,
      "releases": null
    },
    {
      "cop": "GASKA",
      "level": 270,
      "adep": [
        "EDVK"
      ],
      "ades": null,
      "transferType": null,
      "qnh": null,
      "vertical": false,
      "fromSector": "ed/FUL1",
      "toSector": "ed/BBG",
      "remarks": "",
      "rfl": null,
      "runways": null,
      "routeBefore": null,
      "routeAfter": null,
      "releases": null
    },
    {
      "cop": "FEDZA",
      "level": 270,
      "adep": [
        "EDDF",
        "EDFE",
        "EDFZ",
        "ETOU"
      ],
      "ades": null,
      "transferType": null,
      "qnh": null,
      "vertical": false,
      "fromSector": "ed/FUL1",
      "toSector": "ed/HAL",
      "remarks": "",
      "rfl": null,
      "runways": null,
      "routeBefore": null,
      "routeAfter": null,
      "releases": null
    },
    {
      "cop": "KPT",
      "level": 320,
      "adep": null,
      "ades": [
        "LFST",
        "LFGA",
        "LFSB",
        "LFJL"
      ],
      "transferType": null,
      "qnh": null,
      "vertical": false,
      "fromSector": "ed/ALP1",
      "toSector": "ed/FUE",
      "remarks": "L608, 30NM prior KUNOD at FL320",
      "rfl": null,
      "runways": null,
      "routeBefore": null,
      "routeAfter": null,
      "releases": null
    },
    {
      "cop": "NIKWU",
      "level": 320,
      "adep": null,
      "ades": [
        "EDDF"
      ],
      "transferType": null,
      "qnh": null,
      "vertical": false,
      "fromSector": "ed/ALP1",
      "toSector": "ed/FUE",
      "remarks": "",
      "rfl": null,
      "runways": null,
      "routeBefore": null,
      "routeAfter": null,
      "releases": null
    },
    {
      "cop": "LASGA",
      "level": 320,
      "adep": null,
      "ades": [
        "EDDW",
        "EDDV",
        "EDVE",
        "EDBM",
        "ETNW"
      ],
      "transferType": null,
      "qnh": null,
      "vertical": false,
      "fromSector": "ed/ERL1",
      "toSector": "ed/HOF",
      "remarks": "",
      "rfl": null,
      "runways": null,
      "routeBefore": null,
      "routeAfter": null,
      "releases": null
    },
    {
      "cop": "SULED",
      "level": 320,
      "adep": null,
      "ades": [
        "EDDR",
        "EDDS",
        "EDFM",
        "EDFV",
        "EDJA",
        "EDRY",
        "EDRZ",
        "EDTL",
        "EDTY",
        "EDSB",
        "EDTM",
        "ETAR"
      ],
      "transferType": null,
      "qnh": null,
      "vertical": false,
      "fromSector": "ed/SAL1",
      "toSector": "ed/GER",
      "remarks": "",
      "rfl": null,
      "runways": null,
      "routeBefore": null,
      "routeAfter": null,
      "releases": null
    },
    {
      "cop": "SODRO",
      "level": 320,
      "adep": null,
      "ades": [
        "EDDM",
        "EDMA",
        "EDMO"
      ],
      "transferType": null,
      "qnh": null,
      "vertical": false,
      "fromSector": "ed/SAL1",
      "toSector": "ed/HOF",
      "remarks": "15NM before SODRO FL320",
      "rfl": null,
      "runways": null,
      "routeBefore": null,
      "routeAfter": null,
      "releases": null
    },
    {
      "cop": "NOKSI",
      "level": 320,
      "adep": null,
      "ades": [
        "EDDN",
        "EDDS",
        "EDJA"
      ],
      "transferType": null,
      "qnh": null,
      "vertical": false,
      "fromSector": "ed/SPE1",
      "toSector": "ed/MEI",
      "remarks": "20 NM prior NOKSI FL320",
      "rfl": null,
      "runways": null,
      "routeBefore": null,
      "routeAfter": null,
      "releases": null
    },
    {
      "cop": "KOBUS",
      "level": 320,
      "adep": null,
      "ades": [
        "EDQD",
        "EDQM",
        "EDQC",
        "EDQK",
        "EDQT",
        "EDQG",
        "EDQA",
        "ETIC",
        "ETIN",
        "ETHN",
        "LKKV",
        "LKCS"
      ],
      "transferType": null,
      "qnh": null,
      "vertical": false,
      "fromSector": "ed/SPE1",
      "toSector": "ed/MEI",
      "remarks": "",
      "rfl": null,
      "runways": null,
      "routeBefore": null,
      "routeAfter": null,
      "releases": null
    },
    {
      "cop": "AMDID",
      "level": 320,
      "adep": null,
      "ades": [
        "LKCS"
      ],
      "transferType": null,
      "qnh": null,
      "vertical": false,
      "fromSector": "ed/CHI1",
      "toSector": "ed/TRU",
      "remarks": "",
      "rfl": null,
      "runways": null,
      "routeBefore": null,
      "routeAfter": null,
      "releases": null
    },
    {
      "cop": "GESUC",
      "level": 320,
      "adep": null,
      "ades": [
        "EDDF"
      ],
      "transferType": null,
      "qnh": null,
      "vertical": false,
      "fromSector": "ed/ISA1",
      "toSector": "ed/NDG",
      "remarks": "",
      "rfl": null,
      "runways": null,
      "routeBefore": null,
      "routeAfter": null,
      "releases": null
    }
  ]
}
